{
  "cn": {
    "act33sre_zone1": {
      "valid": {
        "startTs": 1745222400,
        "endTs": 1746043199
      }
    }
  },
  "us": {
    "act37side_zone1": {
      "valid": {
        "startTs": 1744113600,
        "endTs": 1745319599
      }
    }
  },
  "jp": {
    "act37side_zone1": {
      "valid": {
        "startTs": 1744077600,
        "endTs": 1745261999
      }
    }
  },
  "kr": {
    "act37side_zone1": {
      "valid": {
        "startTs": 1744077600,
        "endTs": 1745261999
      }
    }
  },
  "tw": {
    "act26sre_zone1": {
      "valid": {
        "startTs": 1744617600,
        "endTs": 1745438399
      }
    }
  }
}
