{
  "cn": {},
  "us": {
    "act25side_zone1": {
      "valid": {
        "startTs": 1699376400,
        "endTs": 1701169199
      }
    }
  },
  "jp": {
    "act17sre_zone1": {
      "valid": {
        "startTs": 1701154800,
        "endTs": 1701975599
      }
    },
    "act17sre_zone2": {
      "valid": {
        "startTs": 1701154800,
        "endTs": 1701975599
      }
    },
    "act17sre_zone3": {
      "valid": {
        "startTs": 1701154800,
        "endTs": 1701975599
      }
    }
  },
  "kr": {},
  "tw": {
    "act23side_zone1": {
      "valid": {
        "startTs": 1700551800,
        "endTs": 1701719999
      }
    }
  }
}
